node.ext.ugm-1.1-nspkg.pth
node/ext/ugm/__init__.py
node/ext/ugm/_api.py
node/ext/ugm/file.py
node/ext/ugm/interfaces.py
node/ext/ugm/tests/__init__.py
node/ext/ugm/tests/test_api.py
node/ext/ugm/tests/test_file.py
node.ext.ugm-1.1.dist-info/LICENSE.rst
node.ext.ugm-1.1.dist-info/METADATA
node.ext.ugm-1.1.dist-info/WHEEL
node.ext.ugm-1.1.dist-info/namespace_packages.txt
node.ext.ugm-1.1.dist-info/top_level.txt
node.ext.ugm-1.1.dist-info/RECORD
